rob/.autoenv
rob/.justfile
rob/.leave
rob/__init__.py
rob/__main__.py
rob/algebra/__init__.py
rob/algebra/problems.py
rob/anagram.py
rob/clean.py
rob/cli/anagram_config.toml
rob/cli/homework_config.toml
rob/cli/night_config.toml
rob/cli config/night_config.toml
rob/config/algebra/config.toml
rob/config/algebra/latex_templates.toml
rob/config/anagram/cli_config.toml
rob/config/clean.toml
rob/config/english/config.toml
rob/config/english/latex_templates.toml
rob/config/homework/config.toml
rob/config/homework/latex_templates.toml
rob/config/project/jinja_template.txt
rob/config/project.toml
rob/configs/night/config.toml
rob/data/sat_words.txt
rob/data/word_list.txt
rob/default_configs/night/config.toml
rob/deprecated/hierarchy.py
rob/deprecated/old_algebra.py
rob/deprecated/old_clean.py
rob/deprecated/old_mail.py
rob/deprecated/robai.py
rob/deprecated/tick.py
rob/english.py
rob/ffmpeg.py
rob/help.py
rob/homework.py
rob/loggers/__init__.py
rob/loggers/tick_logger.py
rob/night.py
rob/parser/__init__.py
rob/parser/clean_parser.py
rob/parser/email_parser.py
rob/parser/ffmpeg_parser.py
rob/parser/reddit_parser.py
rob/parser/tick_parser.py
rob/poetry.lock
rob/poetry.note
rob/problems/__init__.py
rob/problems/algebra.py
rob/problems/chemistry.py
rob/project.py
rob/pyproject.toml
rob/reddit_archive.py
rob/tests/__init__.py
rob/tests/test_algebra_problems.py
rob/tests/test_clean.py
rob/tests/test_cli.py
rob/tests/test_homework_cli.py
rob/tests/test_query.py
rob/tests/test_tomldict.py
rob/ticktick/__init__.py
rob/ticktick/api.py
rob/ticktick/cache.py
rob/ticktick/helpers/__init__.py
rob/ticktick/helpers/constants.py
rob/ticktick/helpers/hex_color.py
rob/ticktick/helpers/time_methods.py
rob/ticktick/helpers/timezones.txt
rob/ticktick/managers/__init__.py
rob/ticktick/managers/check_logged_in.py
rob/ticktick/managers/focus.py
rob/ticktick/managers/habits.py
rob/ticktick/managers/pomo.py
rob/ticktick/managers/projects.py
rob/ticktick/managers/settings.py
robolson-0.3.104.dist-info/METADATA
robolson-0.3.104.dist-info/WHEEL
robolson-0.3.104.dist-info/RECORD
