Metadata-Version: 2.1
Name: robolson
Version: 0.3.104
Summary: My collection of utilty scripts
Author: Rob L Olson
Author-email: rob.louis@gmail.com
Requires-Python: >=3.9.1,<4.0.0
Classifier: Programming Language :: Python :: 3
Classifier: Programming Language :: Python :: 3.10
Classifier: Programming Language :: Python :: 3.11
Classifier: Programming Language :: Python :: 3.12
Classifier: Programming Language :: Python :: 3.13
Requires-Dist: WMI (>=1.5.1,<2.0.0)
Requires-Dist: appdirs (>=1.4.4,<2.0.0)
Requires-Dist: docopt (>=0.6.2,<0.7.0)
Requires-Dist: gkeepapi (>=0.14.2,<0.15.0)
Requires-Dist: google-generativeai (>=0.8.3,<0.9.0)
Requires-Dist: jinja2 (>=3.1.5,<4.0.0)
Requires-Dist: openai (>=1.6.1,<2.0.0)
Requires-Dist: praw (>=7.5.0,<8.0.0)
Requires-Dist: pycaw (>=20230407,<20230408)
Requires-Dist: pydub (==0.25.1)
Requires-Dist: pymultidictionary (>=1.3.2,<2.0.0)
Requires-Dist: readchar (>=4.2.1,<5.0.0)
Requires-Dist: rich (>=11.2.0,<12.0.0)
Requires-Dist: rocketry (>=2.5.1,<3.0.0)
Requires-Dist: survey (>=4.5.4,<5.0.0)
Requires-Dist: sympy (>=1.12,<2.0)
Requires-Dist: toml (>=0.10.2,<0.11.0)
Requires-Dist: typer[all] (>=0.7.0,<0.8.0)
